firex/__init__.py
firex-0.0.2.dist-info/LICENSE
firex-0.0.2.dist-info/METADATA
firex-0.0.2.dist-info/WHEEL
firex-0.0.2.dist-info/top_level.txt
firex-0.0.2.dist-info/RECORD
