Metadata-Version: 2.1
Name: firex
Version: 0.0.2
Summary: Firebase with Python
Home-page: https://github.com/sarmadgulzar/firex
Author: Sarmad Gulzar
Author-email: sarmadgulzar@hotmail.com
License: UNKNOWN
Platform: UNKNOWN
Classifier: Programming Language :: Python :: 3
Classifier: License :: OSI Approved :: MIT License
Classifier: Operating System :: OS Independent
Requires-Python: >=3.6
Requires-Dist: firebase-admin (==5.0.0)
